haxo/__init__.py
haxo/completer.py
haxo/console.py
haxo/repl.py
haxo-0.1.0.dist-info/entry_points.txt
haxo-0.1.0.dist-info/LICENSE
haxo-0.1.0.dist-info/WHEEL
haxo-0.1.0.dist-info/METADATA
haxo-0.1.0.dist-info/RECORD
